README.md
setup.py
DiscBoard/Exceptions.py
DiscBoard/__init__.py
DiscBoard/application.py
DiscBoard/config.py
DiscBoard/guild.py
DiscBoard/user.py
DiscBoard.egg-info/PKG-INFO
DiscBoard.egg-info/SOURCES.txt
DiscBoard.egg-info/dependency_links.txt
DiscBoard.egg-info/requires.txt
DiscBoard.egg-info/top_level.txt