Metadata-Version: 2.1
Name: DiscBoard
Version: 0.3
Summary: A library written for simple backend development of bot dashboards in python
Home-page: UNKNOWN
Author: Pimpek01
Author-email: pimpek.pimposlaw@gmail.com
License: UNKNOWN
Keywords: python,discord.py,Dashboard
Platform: UNKNOWN
Classifier: Development Status :: 1 - Planning
Classifier: Intended Audience :: Developers
Classifier: Programming Language :: Python :: 3
Classifier: Operating System :: Microsoft :: Windows
